Fibnoacci_python_package/__init__.py
Fibnoacci_python_package/fibonacci.py
yash_package_for_useful_functions/__init__.py
yash_package_for_useful_functions/fibonacci.py
Fibnoacci_python_package-1.0.dist-info/LICENSE.txt
Fibnoacci_python_package-1.0.dist-info/METADATA
Fibnoacci_python_package-1.0.dist-info/WHEEL
Fibnoacci_python_package-1.0.dist-info/top_level.txt
Fibnoacci_python_package-1.0.dist-info/RECORD
