Metadata-Version: 2.1
Name: Fibnoacci-python-package
Version: 1.0
Summary: A package for useful functions
Home-page: https://github.com/pypa/sampleproject
Author: Yash
Author-email: yashmahes@gmail.com
License: UNKNOWN
Platform: UNKNOWN
Classifier: Programming Language :: Python :: 3
Classifier: License :: OSI Approved :: MIT License
Classifier: Operating System :: OS Independent
Requires-Dist: pillow (==5.2.0)
